gsimo_lib-0.5.data/scripts/gsimo_lib
gsimo_lib2/__init__.py
gsimo_lib2/mytest2.py
gsimo_lib-0.5.dist-info/METADATA
gsimo_lib-0.5.dist-info/WHEEL
gsimo_lib-0.5.dist-info/top_level.txt
gsimo_lib-0.5.dist-info/RECORD
