Metadata-Version: 2.1
Name: gsimo-lib
Version: 0.5
Summary: A Docker and AWS utility package
Home-page: https://github.com/javatechy/dokr
Author: Guillaume Simo
Author-email: guillaume.simo@hotmail.fr
License: UNKNOWN
Platform: UNKNOWN
Classifier: Programming Language :: Python :: 3
Classifier: License :: OSI Approved :: MIT License
Classifier: Operating System :: OS Independent
